hogql_parser.cpython-312-darwin.so
hogql_parser.dylibs/libantlr4-runtime.4.13.2.dylib
hogql_parser-1.2.10.dist-info/RECORD
hogql_parser-1.2.10.dist-info/WHEEL
hogql_parser-1.2.10.dist-info/top_level.txt
hogql_parser-1.2.10.dist-info/METADATA
hogql_parser-stubs/__init__.pyi
