Metadata-Version: 2.4
Name: hogql_parser
Version: 1.2.10
Summary: HogQL parser for internal PostHog use
Home-page: https://github.com/PostHog/posthog/tree/master/common/hogql_parser
Author: PostHog Inc.
Author-email: hey@posthog.com
Maintainer: PostHog Inc.
Maintainer-email: hey@posthog.com
Classifier: Development Status :: 5 - Production/Stable
Classifier: License :: OSI Approved :: MIT License
Classifier: Operating System :: MacOS
Classifier: Operating System :: POSIX :: Linux
Classifier: Programming Language :: Python
Classifier: Programming Language :: Python :: 3.10
Classifier: Programming Language :: Python :: 3.11
Classifier: Programming Language :: Python :: 3.12
Requires-Python: >=3.10
Dynamic: author
Dynamic: author-email
Dynamic: classifier
Dynamic: description
Dynamic: description-content-type
Dynamic: home-page
Dynamic: maintainer
Dynamic: maintainer-email
Dynamic: requires-python
Dynamic: summary
